geodataflow/pipelineapi.default.settings
geodataflow/pipelineapp.default.settings
geodataflow/eogeo/__init__.py
geodataflow/eogeo/dataset.py
geodataflow/eogeo/productcatalog.py
geodataflow/eogeo/modules/EODAGDriver.py
geodataflow/eogeo/modules/STACDriver.py
geodataflow/spatial/__init__.py
geodataflow/spatial/__meta__.py
geodataflow/spatial/commonutils.py
geodataflow/spatial/dataset.py
geodataflow/spatial/featurelayer.py
geodataflow/spatial/featurestore.py
geodataflow/spatial/gdalcontext.py
geodataflow/spatial/gdalenv.py
geodataflow/spatial/rasterstore.py
geodataflow/spatial/modules/EOProductCatalog.py
geodataflow/spatial/modules/EOProductDataset.py
geodataflow/spatial/modules/FeatureCache.py
geodataflow/spatial/modules/FeatureLimit.py
geodataflow/spatial/modules/FeatureReader.py
geodataflow/spatial/modules/FeatureWriter.py
geodataflow/spatial/modules/GEEProductCatalog.py
geodataflow/spatial/modules/GEEProductDataset.py
geodataflow/spatial/modules/GeometryBuffer.py
geodataflow/spatial/modules/GeometryCentroid.py
geodataflow/spatial/modules/GeometrySpatialRelation.py
geodataflow/spatial/modules/GeometryTransform.py
geodataflow/spatial/modules/RasterCalc.py
geodataflow/spatial/modules/RasterClip.py
geodataflow/spatial/modules/RasterMosaic.py
geodataflow/spatial/modules/RasterPolygonize.py
geodataflow/spatial/modules/RasterReader.py
geodataflow/spatial/modules/RasterSplit.py
geodataflow/spatial/modules/RasterStats.py
geodataflow/spatial/modules/RasterTransform.py
geodataflow/spatial/modules/RasterWriter.py
geodataflow/spatial/modules/TimeseriesPlot.py
geodataflow.spatial-0.2.1.dist-info/LICENSE
geodataflow.spatial-0.2.1.dist-info/METADATA
geodataflow.spatial-0.2.1.dist-info/WHEEL
geodataflow.spatial-0.2.1.dist-info/dependency_links.txt
geodataflow.spatial-0.2.1.dist-info/top_level.txt
geodataflow.spatial-0.2.1.dist-info/RECORD
